sv/con2425_g26/task-1/src/fulladder.sv
/*

 * Generated by Digital. Don't modify this file!

 * Any changes will be lost if this file is regenerated.

 */

module fulladder (
input A,
input B,
input C,
output logic Y,
output logic X
);

assign Y = ((~ A & ~ B & C) | (~ A & B & ~ C) | (A & ~ B & ~ C) | (A & B & C));
assign X = ((A & C) | (A & B) | (B & C));
endmodule

sv/con2425_g26/task-1/src/testbench.sv
`ifndef SYNTHESIS
module testbench();
  // wires for inputs to the module
  logic A, B, C;

  // wires for the outputs of the module
  logic Y, X;

  // create a fulladder and connect the logic elements to it
  fulladder uut (
    .A(A),
    .B(B),
    .C(C),
    .Y(Y),
    .X(X)
  );

  // create dump file
  initial begin
    $dumpfile("fulladder.vcd");
    $dumpvars(0, testbench);
  end

  // this happens only once, you can use this to test your fulladder circuit
  initial begin
    A <= 0;
    B <= 0;
    C <= 0;
    #1
    $display("[Time: %04t, TESTCASE 1] A = %d, B = %d, C = %d results in Y = %d, X = %d", $time, A, B, C, Y, X);
    #1

    A <= 1;
    B <= 0;
    C <= 0;
    #1
    $display("[Time: %04t, TESTCASE 2] A = %d, B = %d, C = %d results in Y = %d, X = %d", $time, A, B, C, Y, X);
    #1

    A <= 0;
    B <= 1;
    C <= 0;
    #1
    $display("[Time: %04t, TESTCASE 3] A = %d, B = %d, C = %d results in Y = %d, X = %d", $time, A, B, C, Y, X);
    #1

    A <= 1;
    B <= 1;
    C <= 0;
    #1
    $display("[Time: %04t, TESTCASE 4] A = %d, B = %d, C = %d results in Y = %d, X = %d", $time, A, B, C, Y, X);
    #1

    A <= 0;
    B <= 0;
    C <= 1;
    #1
    $display("[Time: %04t, TESTCASE 5] A = %d, B = %d, C = %d results in Y = %d, X = %d", $time, A, B, C, Y, X);
    #1

    A <= 1;
    B <= 0;
    C <= 1;
    #1
    $display("[Time: %04t, TESTCASE 6] A = %d, B = %d, C = %d results in Y = %d, X = %d", $time, A, B, C, Y, X);
    #1

    A <= 0;
    B <= 1;
    C <= 1;
    #1
    $display("[Time: %04t, TESTCASE 7] A = %d, B = %d, C = %d results in Y = %d, X = %d", $time, A, B, C, Y, X);
    #1

    A <= 1;
    B <= 1;
    C <= 1;
    #1
    $display("[Time: %04t, TESTCASE 8] A = %d, B = %d, C = %d results in Y = %d, X = %d", $time, A, B, C, Y, X);
    #1

    $finish;
  end

endmodule
`endif

sv/con2425_g26/task-1/src/fulladder.vcd
$date
	Wed Oct 23 15:53:14 2024
$end
$version
	Icarus Verilog
$end
$timescale
	1s
$end
$scope module testbench $end
$var wire 1 ! Y $end
$var wire 1 " X $end
$var reg 1 # A $end
$var reg 1 $ B $end
$var reg 1 % C $end
$scope module uut $end
$var wire 1 # A $end
$var wire 1 $ B $end
$var wire 1 % C $end
$var wire 1 " X $end
$var wire 1 ! Y $end
$upscope $end
$upscope $end
$enddefinitions $end
$comment Show the parameter values. $end
$dumpall
$end
#0
$dumpvars
0%
0$
0#
0"
0!
$end
#2
1!
1#
#4
1!
1$
0#
#6
0!
1"
1#
#8
1!
0"
1%
0$
0#
#10
0!
1"
1#
#12
1$
0#
#14
1!
1#
