sv/con2425_g26/task-1/src/fulladder.sv
module fulladder (
    input  logic a_i,
    input  logic b_i,
    input  logic c_i,

    output logic sum_o,
    output logic c_o
    );

    // add your implementation here
    // Basic boolean logic
    assign sum_o = a_i ^ b_i ^ c_i;
    assign c_o   = (a_i & b_i) | (b_i & c_i) | (a_i & c_i);
endmodule

sv/con2425_g26/task-1/src/addsub.v
module addsub (
	a_i,
	b_i,
	mode_i,
	result_o
);
	input wire [4:0] a_i;
	input wire [4:0] b_i;
	input wire mode_i;
	output wire [4:0] result_o;
	wire [4:0] b_mux;
	wire [5:0] c;
	assign c[0] = mode_i;
	assign b_mux = b_i ^ {5 {mode_i}};
	genvar _gv_i_1;
	generate
		for (_gv_i_1 = 0; _gv_i_1 < 5; _gv_i_1 = _gv_i_1 + 1) begin : FA_CHAIN
			localparam i = _gv_i_1;
			fulladder FA(
				.a_i(a_i[i]),
				.b_i(b_mux[i]),
				.c_i(c[i]),
				.sum_o(result_o[i]),
				.c_o(c[i + 1])
			);
		end
	endgenerate
endmodule

sv/con2425_g26.bak/task-1/src/calculator.v
module calculator (
	clk_i,
	rst_i,
	a_i,
	b_i,
	input_valid_i,
	calc_i,
	mode_i,
	clear_i,
	result_o,
	output_valid_o
);
	reg _sv2v_0;
	input wire clk_i;
	input wire rst_i;
	input wire [4:0] a_i;
	input wire [4:0] b_i;
	input wire input_valid_i;
	input wire calc_i;
	input wire mode_i;
	input wire clear_i;
	output wire [4:0] result_o;
	output wire output_valid_o;
	reg [1:0] state;
	reg [1:0] next_state;
	reg [4:0] reg_a;
	reg [4:0] reg_b;
	addsub addsub_inst(
		.a_i(reg_a),
		.b_i(reg_b),
		.mode_i(mode_i),
		.result_o(result_o)
	);
	always @(*) begin
		if (_sv2v_0)
			;
		case (state)
			2'd0:
				if (input_valid_i)
					next_state = 2'd1;
				else
					next_state = 2'd0;
			2'd1:
				if (input_valid_i)
					next_state = 2'd2;
				else
					next_state = 2'd1;
			2'd2:
				if (calc_i)
					next_state = 2'd0;
				else
					next_state = 2'd2;
			default: next_state = 2'd0;
		endcase
	end
	always @(posedge clk_i or posedge rst_i)
		if (rst_i) begin
			state <= 2'd0;
			reg_a <= 5'b00000;
			reg_b <= 5'b00000;
		end
		else begin
			state <= next_state;
			if (clear_i) begin
				reg_a <= 5'b00000;
				reg_b <= 5'b00000;
				state <= 2'd0;
			end
			else
				case (state)
					2'd0:
						if (input_valid_i)
							reg_a <= a_i;
					2'd1:
						if (input_valid_i)
							reg_b <= b_i;
					2'd2:
						;
					default:
						;
				endcase
		end
	assign output_valid_o = state == 2'd2;
	initial _sv2v_0 = 0;
endmodule

sv/con2425_g26/task-1/tb/calc_tb.sv
`define HALF_PERIOD 10
`define PERIOD 20
`define RESET_DELAY (`HALF_PERIOD + 1)
`define TIMEOUT 100

module calc_tb ();

    // reset generation
    logic reset = 0;
    initial begin
        reset = 0;
        reset = 1;
        #`RESET_DELAY
        reset = 0;
    end

    // clock generation
    logic clk;
    initial clk = 0;
    always begin
        #`HALF_PERIOD clk = ~clk;
    end

    // tick counter
    integer ticks = 0;
    always_ff @(posedge clk or posedge reset) begin
        if (reset) begin
            ticks <= 0;
        end else begin
            ticks <= ticks + 1;
            if (ticks > `TIMEOUT) begin
                $write("Testbench ran into TIMEOUT!\n");
                $finish();
            end
        end
    end

    // dut signals
    logic [4:0] calc_inp_a;
    logic [4:0] calc_inp_b;
    logic       calc_inp_v;
    logic       calc_calc;
    logic       calc_mode;
    logic       calc_clear;

    logic [4:0] calc_result;
    logic       calc_output_v;

    // file descriptors
    integer inp_file, outp_file, ret;


    // device under test (DUT)
    calculator dut (
        .clk_i          ( clk           ),
        .rst_i          ( reset         ),
        .a_i            ( calc_inp_a    ),
        .b_i            ( calc_inp_b    ),
        .input_valid_i  ( calc_inp_v    ),
        .calc_i         ( calc_calc     ),
        .mode_i         ( calc_mode     ),
        .clear_i        ( calc_clear    ),
        .result_o       ( calc_result   ),
        .output_valid_o ( calc_output_v )
        );

    // dump variables for gtkwave
    initial begin
        $dumpfile("calculator.vcd");
        $dumpvars(0, calc_tb);
    end

    task static run_testcase(input integer tc_file, input integer out_file, output integer ret);
        ret = $fscanf(tc_file, "%d %d %b", calc_inp_a, calc_inp_b, calc_mode);
        if (ret) begin
            #`PERIOD
            calc_inp_v = 1'b1;
            #`PERIOD
            #`PERIOD
            calc_inp_v = 1'b0;
            calc_calc  = 1'b1;
            #`PERIOD
            $fdisplay(out_file, "%d %b", calc_result, calc_output_v);
            calc_clear = 1'b1;
            calc_calc = 1'b0;
            #`PERIOD
            #`PERIOD
            calc_clear = 1'b0;
        end
    endtask

    // feel free to add other testcase tasks here

    initial begin
        ret = 1;
        inp_file = $fopen("input.txt", "r");
        outp_file = $fopen("output.txt", "w");
        calc_calc = 0;
        calc_mode = 0;
        calc_clear = 0;
        calc_inp_v = 0;

        while (ret != 0) begin
            run_testcase(inp_file, outp_file, ret);
        end

        // run your custom testcases here
        // note that if you output additional text, the reference file in the
        // 'test' directory must contain your expected output too
        // otherwise 'make test' will consider your testcase as 'failed'
        // (your custom testbench is not graded - only your implementation)

        $finish();
    end

endmodule

sv/con2425_g26.bak/task-1/src/old/calculator.vcd
$date
	Mon Oct 28 12:34:47 2024
$end
$version
	Icarus Verilog
$end
$timescale
	1s
$end
$scope module calc_tb $end
$var wire 5 ! calc_result [4:0] $end
$var wire 1 " calc_output_v $end
$var reg 1 # calc_calc $end
$var reg 1 $ calc_clear $end
$var reg 5 % calc_inp_a [4:0] $end
$var reg 5 & calc_inp_b [4:0] $end
$var reg 1 ' calc_inp_v $end
$var reg 1 ( calc_mode $end
$var reg 1 ) clk $end
$var reg 1 * reset $end
$var integer 32 + inp_file [31:0] $end
$var integer 32 , outp_file [31:0] $end
$var integer 32 - ret [31:0] $end
$var integer 32 . ticks [31:0] $end
$scope module dut $end
$var wire 5 / a_i [4:0] $end
$var wire 5 0 b_i [4:0] $end
$var wire 1 # calc_i $end
$var wire 1 $ clear_i $end
$var wire 1 ) clk_i $end
$var wire 1 ' input_valid_i $end
$var wire 1 ( mode_i $end
$var wire 1 * rst_i $end
$var wire 5 1 result_o [4:0] $end
$var wire 1 " output_valid_o $end
$var reg 1 2 _sv2v_0 $end
$var reg 2 3 next_state [1:0] $end
$var reg 5 4 reg_a [4:0] $end
$var reg 5 5 reg_b [4:0] $end
$var reg 2 6 state [1:0] $end
$scope module addsub_inst $end
$var wire 5 7 a_i [4:0] $end
$var wire 5 8 b_i [4:0] $end
$var wire 5 9 b_mux [4:0] $end
$var wire 1 ( mode_i $end
$var wire 5 : result_o [4:0] $end
$var wire 6 ; c [5:0] $end
$scope begin FA_CHAIN[0] $end
$var parameter 2 < _gv_i_1 $end
$var parameter 32 = i $end
$scope module FA $end
$var wire 1 > a_i $end
$var wire 1 ? b_i $end
$var wire 1 @ c_i $end
$var wire 1 A c_o $end
$var wire 1 B sum_o $end
$upscope $end
$upscope $end
$scope begin FA_CHAIN[1] $end
$var parameter 2 C _gv_i_1 $end
$var parameter 32 D i $end
$scope module FA $end
$var wire 1 E a_i $end
$var wire 1 F b_i $end
$var wire 1 G c_i $end
$var wire 1 H c_o $end
$var wire 1 I sum_o $end
$upscope $end
$upscope $end
$scope begin FA_CHAIN[2] $end
$var parameter 3 J _gv_i_1 $end
$var parameter 32 K i $end
$scope module FA $end
$var wire 1 L a_i $end
$var wire 1 M b_i $end
$var wire 1 N c_i $end
$var wire 1 O c_o $end
$var wire 1 P sum_o $end
$upscope $end
$upscope $end
$scope begin FA_CHAIN[3] $end
$var parameter 3 Q _gv_i_1 $end
$var parameter 32 R i $end
$scope module FA $end
$var wire 1 S a_i $end
$var wire 1 T b_i $end
$var wire 1 U c_i $end
$var wire 1 V c_o $end
$var wire 1 W sum_o $end
$upscope $end
$upscope $end
$scope begin FA_CHAIN[4] $end
$var parameter 4 X _gv_i_1 $end
$var parameter 32 Y i $end
$scope module FA $end
$var wire 1 Z a_i $end
$var wire 1 [ b_i $end
$var wire 1 \ c_i $end
$var wire 1 ] c_o $end
$var wire 1 ^ sum_o $end
$upscope $end
$upscope $end
$upscope $end
$upscope $end
$scope task run_testcase $end
$var integer 32 _ out_file [31:0] $end
$var integer 32 ` ret [31:0] $end
$var integer 32 a tc_file [31:0] $end
$upscope $end
$upscope $end
$enddefinitions $end
$comment Show the parameter values. $end
$dumpall
b100 Y
b100 X
b11 R
b11 Q
b10 K
b10 J
b1 D
b1 C
b0 =
b0 <
$end
#0
$dumpvars
b0 a
b11111111111111111111111111111111 `
b10000000000000000000000000000011 _
0^
0]
0\
0[
0Z
0W
0V
0U
0T
0S
0P
0O
0N
0M
0L
0I
0H
0G
0F
0E
0B
0A
0@
0?
0>
b0 ;
b0 :
b0 9
b0 8
b0 7
b0 6
b0 5
b0 4
b0 3
02
b0 1
bx 0
bx /
b0 .
b1 -
b10000000000000000000000000000011 ,
b0 +
1*
0)
0(
0'
bx &
bx %
0$
0#
0"
b0 !
$end
#10
1)
#11
0*
#20
b1 3
0)
1'
#30
xB
xI
xP
xW
bx !
bx 1
bx :
x^
x>
xE
xL
xS
xZ
b10 3
bx 4
bx 7
b1 6
b1 .
1)
#40
0)
#50
xG
xN
xU
x\
xA
xH
xO
xV
bx0 ;
x]
x?
xF
xM
xT
x[
bx 9
b10 .
bx 5
bx 8
1"
b10 6
1)
#60
b0 3
0)
1#
0'
#70
0"
b0 6
b11 .
1)
#80
0)
0#
1$
#90
0P
0W
0^
0N
0U
0\
0I
0H
0O
0V
0]
0G
b0 !
b0 1
b0 :
0B
b0 ;
0A
0?
0F
0M
0T
0[
b0 9
0>
0E
0L
0S
0Z
b100 .
b0 5
b0 8
b0 4
b0 7
1)
#100
0)
#110
b101 .
1)
#120
0)
b11111111111111111111111111111111 -
0$
#130
b110 .
1)
#140
b1 3
0)
1'
#150
xB
xI
xP
xW
bx !
bx 1
bx :
x^
x>
xE
xL
xS
xZ
b10 3
bx 4
bx 7
b1 6
b111 .
1)
#160
0)
#170
xG
xN
xU
x\
xA
xH
xO
xV
bx0 ;
x]
x?
xF
xM
xT
x[
bx 9
b1000 .
bx 5
bx 8
1"
b10 6
1)
#180
b0 3
0)
1#
0'
#190
0"
b0 6
b1001 .
1)
#200
0)
0#
1$
#210
0P
0W
0^
0N
0U
0\
0I
0H
0O
0V
0]
0G
b0 !
b0 1
b0 :
0B
b0 ;
0A
0?
0F
0M
0T
0[
b0 9
0>
0E
0L
0S
0Z
b1010 .
b0 5
b0 8
b0 4
b0 7
1)
#220
0)
#230
b1011 .
1)
#240
0)
0$
#250
b1100 .
1)
#260
b1 3
0)
1'
#270
xB
xI
xP
xW
bx !
bx 1
bx :
x^
x>
xE
xL
xS
xZ
b10 3
bx 4
bx 7
b1 6
b1101 .
1)
#280
0)
#290
xG
xN
xU
x\
xA
xH
xO
xV
bx0 ;
x]
x?
xF
xM
xT
x[
bx 9
b1110 .
bx 5
bx 8
1"
b10 6
1)
#300
b0 3
0)
1#
0'
#310
0"
b0 6
b1111 .
1)
#320
0)
0#
1$
#330
0P
0W
0^
0N
0U
0\
0I
0H
0O
0V
0]
0G
b0 !
b0 1
b0 :
0B
b0 ;
0A
0?
0F
0M
0T
0[
b0 9
0>
0E
0L
0S
0Z
b10000 .
b0 5
b0 8
b0 4
b0 7
1)
#340
0)
#350
b10001 .
1)
#360
0)
0$
#370
b10010 .
1)
#380
b1 3
0)
1'
#390
xB
xI
xP
xW
bx !
bx 1
bx :
x^
x>
xE
xL
xS
xZ
b10 3
bx 4
bx 7
b1 6
b10011 .
1)
#400
0)
#410
xG
xN
xU
x\
xA
xH
xO
xV
bx0 ;
x]
x?
xF
xM
xT
x[
bx 9
b10100 .
bx 5
bx 8
1"
b10 6
1)
#420
b0 3
0)
1#
0'
#430
0"
b0 6
b10101 .
1)
#440
0)
0#
1$
#450
0P
0W
0^
0N
0U
0\
0I
0H
0O
0V
0]
0G
b0 !
b0 1
b0 :
0B
b0 ;
0A
0?
0F
0M
0T
0[
b0 9
0>
0E
0L
0S
0Z
b10110 .
b0 5
b0 8
b0 4
b0 7
1)
#460
0)
#470
b10111 .
1)
#480
0)
0$
#490
b11000 .
1)
#500
b1 3
0)
1'
#510
xB
xI
xP
xW
bx !
bx 1
bx :
x^
x>
xE
xL
xS
xZ
b10 3
bx 4
bx 7
b1 6
b11001 .
1)
#520
0)
#530
xG
xN
xU
x\
xA
xH
xO
xV
bx0 ;
x]
x?
xF
xM
xT
x[
bx 9
b11010 .
bx 5
bx 8
1"
b10 6
1)
#540
b0 3
0)
1#
0'
#550
0"
b0 6
b11011 .
1)
#560
0)
0#
1$
#570
0P
0W
0^
0N
0U
0\
0I
0H
0O
0V
0]
0G
b0 !
b0 1
b0 :
0B
b0 ;
0A
0?
0F
0M
0T
0[
b0 9
0>
0E
0L
0S
0Z
b11100 .
b0 5
b0 8
b0 4
b0 7
1)
#580
0)
#590
b11101 .
1)
#600
0)
0$
#610
b11110 .
1)
#620
b1 3
0)
1'
#630
xB
xI
xP
xW
bx !
bx 1
bx :
x^
x>
xE
xL
xS
xZ
b10 3
bx 4
bx 7
b1 6
b11111 .
1)
#640
0)
#650
xG
xN
xU
x\
xA
xH
xO
xV
bx0 ;
x]
x?
xF
xM
xT
x[
bx 9
b100000 .
bx 5
bx 8
1"
b10 6
1)
#660
b0 3
0)
1#
0'
#670
0"
b0 6
b100001 .
1)
#680
0)
0#
1$
#690
0P
0W
0^
0N
0U
0\
0I
0H
0O
0V
0]
0G
b0 !
b0 1
b0 :
0B
b0 ;
0A
0?
0F
0M
0T
0[
b0 9
0>
0E
0L
0S
0Z
b100010 .
b0 5
b0 8
b0 4
b0 7
1)
#700
0)
#710
b100011 .
1)
#720
0)
0$
#730
b100100 .
1)
#740
b1 3
0)
1'
#750
xB
xI
xP
xW
bx !
bx 1
bx :
x^
x>
xE
xL
xS
xZ
b10 3
bx 4
bx 7
b1 6
b100101 .
1)
#760
0)
#770
xG
xN
xU
x\
xA
xH
xO
xV
bx0 ;
x]
x?
xF
xM
xT
x[
bx 9
b100110 .
bx 5
bx 8
1"
b10 6
1)
#780
b0 3
0)
1#
0'
#790
0"
b0 6
b100111 .
1)
#800
0)
0#
1$
#810
0P
0W
0^
0N
0U
0\
0I
0H
0O
0V
0]
0G
b0 !
b0 1
b0 :
0B
b0 ;
0A
0?
0F
0M
0T
0[
b0 9
0>
0E
0L
0S
0Z
b101000 .
b0 5
b0 8
b0 4
b0 7
1)
#820
0)
#830
b101001 .
1)
#840
0)
0$
#850
b101010 .
1)
#860
b1 3
0)
1'
#870
xB
xI
xP
xW
bx !
bx 1
bx :
x^
x>
xE
xL
xS
xZ
b10 3
bx 4
bx 7
b1 6
b101011 .
1)
#880
0)
#890
xG
xN
xU
x\
xA
xH
xO
xV
bx0 ;
x]
x?
xF
xM
xT
x[
bx 9
b101100 .
bx 5
bx 8
1"
b10 6
1)
#900
b0 3
0)
1#
0'
#910
0"
b0 6
b101101 .
1)
#920
0)
0#
1$
#930
0P
0W
0^
0N
0U
0\
0I
0H
0O
0V
0]
0G
b0 !
b0 1
b0 :
0B
b0 ;
0A
0?
0F
0M
0T
0[
b0 9
0>
0E
0L
0S
0Z
b101110 .
b0 5
b0 8
b0 4
b0 7
1)
#940
0)
#950
b101111 .
1)
#960
0)
0$
#970
b110000 .
1)
#980
b1 3
0)
1'
#990
xB
xI
xP
xW
bx !
bx 1
bx :
x^
x>
xE
xL
xS
xZ
b10 3
bx 4
bx 7
b1 6
b110001 .
1)
#1000
0)
#1010
xG
xN
xU
x\
xA
xH
xO
xV
bx0 ;
x]
x?
xF
xM
xT
x[
bx 9
b110010 .
bx 5
bx 8
1"
b10 6
1)
#1020
b0 3
0)
1#
0'
#1030
0"
b0 6
b110011 .
1)
#1040
0)
0#
1$
#1050
0P
0W
0^
0N
0U
0\
0I
0H
0O
0V
0]
0G
b0 !
b0 1
b0 :
0B
b0 ;
0A
0?
0F
0M
0T
0[
b0 9
0>
0E
0L
0S
0Z
b110100 .
b0 5
b0 8
b0 4
b0 7
1)
#1060
0)
#1070
b110101 .
1)
#1080
0)
0$
#1090
b110110 .
1)
#1100
b1 3
0)
1'
#1110
xB
xI
xP
xW
bx !
bx 1
bx :
x^
x>
xE
xL
xS
xZ
b10 3
bx 4
bx 7
b1 6
b110111 .
1)
#1120
0)
#1130
xG
xN
xU
x\
xA
xH
xO
xV
bx0 ;
x]
x?
xF
xM
xT
x[
bx 9
b111000 .
bx 5
bx 8
1"
b10 6
1)
#1140
b0 3
0)
1#
0'
#1150
0"
b0 6
b111001 .
1)
#1160
0)
0#
1$
#1170
0P
0W
0^
0N
0U
0\
0I
0H
0O
0V
0]
0G
b0 !
b0 1
b0 :
0B
b0 ;
0A
0?
0F
0M
0T
0[
b0 9
0>
0E
0L
0S
0Z
b111010 .
b0 5
b0 8
b0 4
b0 7
1)
#1180
0)
#1190
b111011 .
1)
#1200
0)
0$
#1210
b111100 .
1)
#1220
b1 3
0)
1'
#1230
xB
xI
xP
xW
bx !
bx 1
bx :
x^
x>
xE
xL
xS
xZ
b10 3
bx 4
bx 7
b1 6
b111101 .
1)
#1240
0)
#1250
xG
xN
xU
x\
xA
xH
xO
xV
bx0 ;
x]
x?
xF
xM
xT
x[
bx 9
b111110 .
bx 5
bx 8
1"
b10 6
1)
#1260
b0 3
0)
1#
0'
#1270
0"
b0 6
b111111 .
1)
#1280
0)
0#
1$
#1290
0P
0W
0^
0N
0U
0\
0I
0H
0O
0V
0]
0G
b0 !
b0 1
b0 :
0B
b0 ;
0A
0?
0F
0M
0T
0[
b0 9
0>
0E
0L
0S
0Z
b1000000 .
b0 5
b0 8
b0 4
b0 7
1)
#1300
0)
#1310
b1000001 .
1)
#1320
0)
0$
#1330
b1000010 .
1)
#1340
b1 3
0)
1'
#1350
xB
xI
xP
xW
bx !
bx 1
bx :
x^
x>
xE
xL
xS
xZ
b10 3
bx 4
bx 7
b1 6
b1000011 .
1)
#1360
0)
#1370
xG
xN
xU
x\
xA
xH
xO
xV
bx0 ;
x]
x?
xF
xM
xT
x[
bx 9
b1000100 .
bx 5
bx 8
1"
b10 6
1)
#1380
b0 3
0)
1#
0'
#1390
0"
b0 6
b1000101 .
1)
#1400
0)
0#
1$
#1410
0P
0W
0^
0N
0U
0\
0I
0H
0O
0V
0]
0G
b0 !
b0 1
b0 :
0B
b0 ;
0A
0?
0F
0M
0T
0[
b0 9
0>
0E
0L
0S
0Z
b1000110 .
b0 5
b0 8
b0 4
b0 7
1)
#1420
0)
#1430
b1000111 .
1)
#1440
0)
0$
#1450
b1001000 .
1)
#1460
b1 3
0)
1'
#1470
xB
xI
xP
xW
bx !
bx 1
bx :
x^
x>
xE
xL
xS
xZ
b10 3
bx 4
bx 7
b1 6
b1001001 .
1)
#1480
0)
#1490
xG
xN
xU
x\
xA
xH
xO
xV
bx0 ;
x]
x?
xF
xM
xT
x[
bx 9
b1001010 .
bx 5
bx 8
1"
b10 6
1)
#1500
b0 3
0)
1#
0'
#1510
0"
b0 6
b1001011 .
1)
#1520
0)
0#
1$
#1530
0P
0W
0^
0N
0U
0\
0I
0H
0O
0V
0]
0G
b0 !
b0 1
b0 :
0B
b0 ;
0A
0?
0F
0M
0T
0[
b0 9
0>
0E
0L
0S
0Z
b1001100 .
b0 5
b0 8
b0 4
b0 7
1)
#1540
0)
#1550
b1001101 .
1)
#1560
0)
0$
#1570
b1001110 .
1)
#1580
b1 3
0)
1'
#1590
xB
xI
xP
xW
bx !
bx 1
bx :
x^
x>
xE
xL
xS
xZ
b10 3
bx 4
bx 7
b1 6
b1001111 .
1)
#1600
0)
#1610
xG
xN
xU
x\
xA
xH
xO
xV
bx0 ;
x]
x?
xF
xM
xT
x[
bx 9
b1010000 .
bx 5
bx 8
1"
b10 6
1)
#1620
b0 3
0)
1#
0'
#1630
0"
b0 6
b1010001 .
1)
#1640
0)
0#
1$
#1650
0P
0W
0^
0N
0U
0\
0I
0H
0O
0V
0]
0G
b0 !
b0 1
b0 :
0B
b0 ;
0A
0?
0F
0M
0T
0[
b0 9
0>
0E
0L
0S
0Z
b1010010 .
b0 5
b0 8
b0 4
b0 7
1)
#1660
0)
#1670
b1010011 .
1)
#1680
0)
0$
#1690
b1010100 .
1)
#1700
b1 3
0)
1'
#1710
xB
xI
xP
xW
bx !
bx 1
bx :
x^
x>
xE
xL
xS
xZ
b10 3
bx 4
bx 7
b1 6
b1010101 .
1)
#1720
0)
#1730
xG
xN
xU
x\
xA
xH
xO
xV
bx0 ;
x]
x?
xF
xM
xT
x[
bx 9
b1010110 .
bx 5
bx 8
1"
b10 6
1)
#1740
b0 3
0)
1#
0'
#1750
0"
b0 6
b1010111 .
1)
#1760
0)
0#
1$
#1770
0P
0W
0^
0N
0U
0\
0I
0H
0O
0V
0]
0G
b0 !
b0 1
b0 :
0B
b0 ;
0A
0?
0F
0M
0T
0[
b0 9
0>
0E
0L
0S
0Z
b1011000 .
b0 5
b0 8
b0 4
b0 7
1)
#1780
0)
#1790
b1011001 .
1)
#1800
0)
0$
#1810
b1011010 .
1)
#1820
b1 3
0)
1'
#1830
xB
xI
xP
xW
bx !
bx 1
bx :
x^
x>
xE
xL
xS
xZ
b10 3
bx 4
bx 7
b1 6
b1011011 .
1)
#1840
0)
#1850
xG
xN
xU
x\
xA
xH
xO
xV
bx0 ;
x]
x?
xF
xM
xT
x[
bx 9
b1011100 .
bx 5
bx 8
1"
b10 6
1)
#1860
b0 3
0)
1#
0'
#1870
0"
b0 6
b1011101 .
1)
#1880
0)
0#
1$
#1890
0P
0W
0^
0N
0U
0\
0I
0H
0O
0V
0]
0G
b0 !
b0 1
b0 :
0B
b0 ;
0A
0?
0F
0M
0T
0[
b0 9
0>
0E
0L
0S
0Z
b1011110 .
b0 5
b0 8
b0 4
b0 7
1)
#1900
0)
#1910
b1011111 .
1)
#1920
0)
0$
#1930
b1100000 .
1)
#1940
b1 3
0)
1'
#1950
xB
xI
xP
xW
bx !
bx 1
bx :
x^
x>
xE
xL
xS
xZ
b10 3
bx 4
bx 7
b1 6
b1100001 .
1)
#1960
0)
#1970
xG
xN
xU
x\
xA
xH
xO
xV
bx0 ;
x]
x?
xF
xM
xT
x[
bx 9
b1100010 .
bx 5
bx 8
1"
b10 6
1)
#1980
b0 3
0)
1#
0'
#1990
0"
b0 6
b1100011 .
1)
#2000
0)
0#
1$
#2010
0P
0W
0^
0N
0U
0\
0I
0H
0O
0V
0]
0G
b0 !
b0 1
b0 :
0B
b0 ;
0A
0?
0F
0M
0T
0[
b0 9
0>
0E
0L
0S
0Z
b1100100 .
b0 5
b0 8
b0 4
b0 7
1)
#2020
0)
#2030
b1100101 .
1)
#2040
0)
0$
#2050
b1100110 .
1)
