sv/SystemVerilog/common/cmos_cells.v
module BUF(A, Y);
input A;
output Y;
//assign #10 Y = A; // example assignment with delay
assign Y = A;
endmodule

module NOT(A, Y);
input A;
output Y;
//assign #10 Y = ~A; // example assignment with delay
assign Y = ~A;
endmodule

module NAND(A, B, Y);
input A, B;
output Y;
//assign #10 Y = ~(A & B);  // example assignment with delay
assign Y = ~(A & B);
endmodule

module NOR(A, B, Y);
input A, B;
output Y;
//assign #10 Y = ~(A | B);	// example assignment with delay
assign Y = ~(A | B);
endmodule

module DFF(C, D, Q);
input C, D;
output reg Q;
always @(posedge C)
	Q <= D;
endmodule

module DFFSR(C, D, Q, S, R);
input C, D, S, R;
output reg Q;
always @(posedge C, posedge S, posedge R)
	if (S)
		Q <= 1'b1;
	else if (R)
		Q <= 1'b0;
	else
		Q <= D;
endmodule

SystemVerilog/con03.02_add_sub_machine/syn.v
/* Generated by Yosys 0.46+11 (git sha1 a00137c2f, clang++ 14.0.0-1ubuntu1.1 -fPIC -O3) */

(* src = "add_sub_machine.sv:1.1-33.10" *)
module add_sub_machine(clk_i, reset_i, addsub_i, out_o);
  wire _00_;
  wire _01_;
  wire _02_;
  wire _03_;
  wire _04_;
  wire _05_;
  wire _06_;
  wire _07_;
  wire _08_;
  wire _09_;
  wire _10_;
  wire _11_;
  wire _12_;
  wire _13_;
  wire _14_;
  wire _15_;
  wire _16_;
  wire _17_;
  wire _18_;
  wire _19_;
  wire _20_;
  wire _21_;
  wire _22_;
  wire _23_;
  wire _24_;
  wire _25_;
  wire _26_;
  wire _27_;
  wire _28_;
  wire _29_;
  wire _30_;
  (* src = "add_sub_machine.sv:4.17-4.25" *)
  input addsub_i;
  wire addsub_i;
  (* src = "add_sub_machine.sv:2.17-2.22" *)
  input clk_i;
  wire clk_i;
  (* src = "add_sub_machine.sv:5.24-5.29" *)
  output [3:0] out_o;
  wire [3:0] out_o;
  (* src = "add_sub_machine.sv:3.17-3.24" *)
  input reset_i;
  wire reset_i;
  (* src = "add_sub_machine.sv:8.26-8.33" *)
  wire [3:0] value_n;
  (* src = "add_sub_machine.sv:8.17-8.24" *)
  wire [3:0] value_p;
  NOT _31_ (
    .A(addsub_i),
    .Y(_00_)
  );
  NOT _32_ (
    .A(value_p[1]),
    .Y(_01_)
  );
  NOT _33_ (
    .A(value_p[2]),
    .Y(_02_)
  );
  NOT _34_ (
    .A(value_p[0]),
    .Y(value_n[0])
  );
  NOT _35_ (
    .A(value_p[3]),
    .Y(_03_)
  );
  NOR _36_ (
    .A(addsub_i),
    .B(value_p[1]),
    .Y(_04_)
  );
  NOT _37_ (
    .A(_04_),
    .Y(_05_)
  );
  NOR _38_ (
    .A(_00_),
    .B(_01_),
    .Y(_06_)
  );
  NAND _39_ (
    .A(addsub_i),
    .B(value_p[1]),
    .Y(_07_)
  );
  NOR _40_ (
    .A(_04_),
    .B(_06_),
    .Y(_08_)
  );
  NAND _41_ (
    .A(_05_),
    .B(_07_),
    .Y(_09_)
  );
  NOR _42_ (
    .A(value_n[0]),
    .B(_09_),
    .Y(_10_)
  );
  NAND _43_ (
    .A(value_p[0]),
    .B(_08_),
    .Y(_11_)
  );
  NOR _44_ (
    .A(value_p[0]),
    .B(_08_),
    .Y(_12_)
  );
  NOR _45_ (
    .A(_10_),
    .B(_12_),
    .Y(value_n[1])
  );
  NOR _46_ (
    .A(_06_),
    .B(_10_),
    .Y(_13_)
  );
  NAND _47_ (
    .A(_07_),
    .B(_11_),
    .Y(_14_)
  );
  NOR _48_ (
    .A(_00_),
    .B(value_p[2]),
    .Y(_15_)
  );
  NAND _49_ (
    .A(addsub_i),
    .B(_02_),
    .Y(_16_)
  );
  NOR _50_ (
    .A(addsub_i),
    .B(_02_),
    .Y(_17_)
  );
  NAND _51_ (
    .A(_00_),
    .B(value_p[2]),
    .Y(_18_)
  );
  NOR _52_ (
    .A(_15_),
    .B(_17_),
    .Y(_19_)
  );
  NAND _53_ (
    .A(_16_),
    .B(_18_),
    .Y(_20_)
  );
  NAND _54_ (
    .A(_13_),
    .B(_20_),
    .Y(_21_)
  );
  NAND _55_ (
    .A(_14_),
    .B(_19_),
    .Y(_22_)
  );
  NAND _56_ (
    .A(_21_),
    .B(_22_),
    .Y(value_n[2])
  );
  NOR _57_ (
    .A(_14_),
    .B(_16_),
    .Y(_23_)
  );
  NAND _58_ (
    .A(_13_),
    .B(_15_),
    .Y(_24_)
  );
  NOR _59_ (
    .A(_11_),
    .B(_18_),
    .Y(_25_)
  );
  NAND _60_ (
    .A(_10_),
    .B(_17_),
    .Y(_26_)
  );
  NOR _61_ (
    .A(_23_),
    .B(_25_),
    .Y(_27_)
  );
  NAND _62_ (
    .A(_24_),
    .B(_26_),
    .Y(_28_)
  );
  NOR _63_ (
    .A(value_p[3]),
    .B(_28_),
    .Y(_29_)
  );
  NOR _64_ (
    .A(_03_),
    .B(_27_),
    .Y(_30_)
  );
  NOR _65_ (
    .A(_29_),
    .B(_30_),
    .Y(value_n[3])
  );
  (* src = "add_sub_machine.sv:11.5-16.8" *)
  DFFSR _66_ (
    .C(clk_i),
    .D(value_n[0]),
    .Q(value_p[0]),
    .R(reset_i),
    .S(1'h0)
  );
  (* src = "add_sub_machine.sv:11.5-16.8" *)
  DFFSR _67_ (
    .C(clk_i),
    .D(value_n[1]),
    .Q(value_p[1]),
    .R(reset_i),
    .S(1'h0)
  );
  (* src = "add_sub_machine.sv:11.5-16.8" *)
  DFFSR _68_ (
    .C(clk_i),
    .D(value_n[2]),
    .Q(value_p[2]),
    .R(reset_i),
    .S(1'h0)
  );
  (* src = "add_sub_machine.sv:11.5-16.8" *)
  DFFSR _69_ (
    .C(clk_i),
    .D(value_n[3]),
    .Q(value_p[3]),
    .R(reset_i),
    .S(1'h0)
  );
  assign #30ns out_o = value_p;
endmodule

sv/SystemVerilog/con03.02_add_sub_machine/testbench.sv
`ifndef SYNTHESIS
`timescale 100ns/1ns
module testbench();
  // wires for inputs to the module
  logic clk;
  logic reset;
  logic addsub;

  // wires for the outputs of the module
  logic [3:0] out;

  // create an add-sub module and connect the logic elements to it
  add_sub_machine fsm(
    .clk_i(clk),
    .reset_i(reset),
    .addsub_i(addsub),
    .out_o(out)
  );

  // create dump file
  initial begin
    $dumpfile("add_sub_machine.vcd");
    $dumpvars(0, testbench);
  end

  // create clock
  integer cc = 0;
  integer i;
  initial begin
    clk = 0;

    for (i = 0; i < 40; i++) begin
      if (clk == 0)
        cc = cc + 1;

      clk = ~clk;
      #1;
    end

    $finish();
  end

  // handle reset
  initial reset = 1;
  always begin
    #1;
    reset = 0;
  end

  // testbench
  initial begin
    // executed whenever some value in the format string changes
    $monitor("[STATE] clock cycle = %d  reset_i = %d, addsub_i = %d, out_o = %d", cc, reset, addsub, out);
  end

  // define input signals as time passes
  initial begin
    addsub = 0;
    #5;
    addsub = 1;
    #5;
    addsub = 0;
  end

endmodule
`endif

SystemVerilog/con03.02_add_sub_machine/add_sub_machine.vcd
$date
	Sun Oct 13 22:53:13 2024
$end
$version
	Icarus Verilog
$end
$timescale
	1ns
$end
$scope module testbench $end
$var wire 4 ! out [3:0] $end
$var reg 1 " addsub $end
$var reg 1 # clk $end
$var reg 1 $ reset $end
$var integer 32 % cc [31:0] $end
$var integer 32 & i [31:0] $end
$scope module fsm $end
$var wire 1 " addsub_i $end
$var wire 1 # clk_i $end
$var wire 4 ' out_o [3:0] $end
$var wire 1 $ reset_i $end
$var wire 4 ( value_p [3:0] $end
$var wire 4 ) value_n [3:0] $end
$var wire 1 * _30_ $end
$var wire 1 + _29_ $end
$var wire 1 , _28_ $end
$var wire 1 - _27_ $end
$var wire 1 . _26_ $end
$var wire 1 / _25_ $end
$var wire 1 0 _24_ $end
$var wire 1 1 _23_ $end
$var wire 1 2 _22_ $end
$var wire 1 3 _21_ $end
$var wire 1 4 _20_ $end
$var wire 1 5 _19_ $end
$var wire 1 6 _18_ $end
$var wire 1 7 _17_ $end
$var wire 1 8 _16_ $end
$var wire 1 9 _15_ $end
$var wire 1 : _14_ $end
$var wire 1 ; _13_ $end
$var wire 1 < _12_ $end
$var wire 1 = _11_ $end
$var wire 1 > _10_ $end
$var wire 1 ? _09_ $end
$var wire 1 @ _08_ $end
$var wire 1 A _07_ $end
$var wire 1 B _06_ $end
$var wire 1 C _05_ $end
$var wire 1 D _04_ $end
$var wire 1 E _03_ $end
$var wire 1 F _02_ $end
$var wire 1 G _01_ $end
$var wire 1 H _00_ $end
$scope module _31_ $end
$var wire 1 " A $end
$var wire 1 H Y $end
$upscope $end
$scope module _32_ $end
$var wire 1 I A $end
$var wire 1 G Y $end
$upscope $end
$scope module _33_ $end
$var wire 1 J A $end
$var wire 1 F Y $end
$upscope $end
$scope module _34_ $end
$var wire 1 K A $end
$var wire 1 L Y $end
$upscope $end
$scope module _35_ $end
$var wire 1 M A $end
$var wire 1 E Y $end
$upscope $end
$scope module _36_ $end
$var wire 1 " A $end
$var wire 1 N B $end
$var wire 1 D Y $end
$upscope $end
$scope module _37_ $end
$var wire 1 D A $end
$var wire 1 C Y $end
$upscope $end
$scope module _38_ $end
$var wire 1 H A $end
$var wire 1 G B $end
$var wire 1 B Y $end
$upscope $end
$scope module _39_ $end
$var wire 1 " A $end
$var wire 1 O B $end
$var wire 1 A Y $end
$upscope $end
$scope module _40_ $end
$var wire 1 D A $end
$var wire 1 B B $end
$var wire 1 @ Y $end
$upscope $end
$scope module _41_ $end
$var wire 1 C A $end
$var wire 1 A B $end
$var wire 1 ? Y $end
$upscope $end
$scope module _42_ $end
$var wire 1 P A $end
$var wire 1 ? B $end
$var wire 1 > Y $end
$upscope $end
$scope module _43_ $end
$var wire 1 Q A $end
$var wire 1 @ B $end
$var wire 1 = Y $end
$upscope $end
$scope module _44_ $end
$var wire 1 R A $end
$var wire 1 @ B $end
$var wire 1 < Y $end
$upscope $end
$scope module _45_ $end
$var wire 1 > A $end
$var wire 1 < B $end
$var wire 1 S Y $end
$upscope $end
$scope module _46_ $end
$var wire 1 B A $end
$var wire 1 > B $end
$var wire 1 ; Y $end
$upscope $end
$scope module _47_ $end
$var wire 1 A A $end
$var wire 1 = B $end
$var wire 1 : Y $end
$upscope $end
$scope module _48_ $end
$var wire 1 H A $end
$var wire 1 T B $end
$var wire 1 9 Y $end
$upscope $end
$scope module _49_ $end
$var wire 1 " A $end
$var wire 1 F B $end
$var wire 1 8 Y $end
$upscope $end
$scope module _50_ $end
$var wire 1 " A $end
$var wire 1 F B $end
$var wire 1 7 Y $end
$upscope $end
$scope module _51_ $end
$var wire 1 H A $end
$var wire 1 U B $end
$var wire 1 6 Y $end
$upscope $end
$scope module _52_ $end
$var wire 1 9 A $end
$var wire 1 7 B $end
$var wire 1 5 Y $end
$upscope $end
$scope module _53_ $end
$var wire 1 8 A $end
$var wire 1 6 B $end
$var wire 1 4 Y $end
$upscope $end
$scope module _54_ $end
$var wire 1 ; A $end
$var wire 1 4 B $end
$var wire 1 3 Y $end
$upscope $end
$scope module _55_ $end
$var wire 1 : A $end
$var wire 1 5 B $end
$var wire 1 2 Y $end
$upscope $end
$scope module _56_ $end
$var wire 1 3 A $end
$var wire 1 2 B $end
$var wire 1 V Y $end
$upscope $end
$scope module _57_ $end
$var wire 1 : A $end
$var wire 1 8 B $end
$var wire 1 1 Y $end
$upscope $end
$scope module _58_ $end
$var wire 1 ; A $end
$var wire 1 9 B $end
$var wire 1 0 Y $end
$upscope $end
$scope module _59_ $end
$var wire 1 = A $end
$var wire 1 6 B $end
$var wire 1 / Y $end
$upscope $end
$scope module _60_ $end
$var wire 1 > A $end
$var wire 1 7 B $end
$var wire 1 . Y $end
$upscope $end
$scope module _61_ $end
$var wire 1 1 A $end
$var wire 1 / B $end
$var wire 1 - Y $end
$upscope $end
$scope module _62_ $end
$var wire 1 0 A $end
$var wire 1 . B $end
$var wire 1 , Y $end
$upscope $end
$scope module _63_ $end
$var wire 1 W A $end
$var wire 1 , B $end
$var wire 1 + Y $end
$upscope $end
$scope module _64_ $end
$var wire 1 E A $end
$var wire 1 - B $end
$var wire 1 * Y $end
$upscope $end
$scope module _65_ $end
$var wire 1 + A $end
$var wire 1 * B $end
$var wire 1 X Y $end
$upscope $end
$scope module _66_ $end
$var wire 1 # C $end
$var wire 1 Y D $end
$var wire 1 $ R $end
$var wire 1 Z S $end
$var reg 1 [ Q $end
$upscope $end
$scope module _67_ $end
$var wire 1 # C $end
$var wire 1 \ D $end
$var wire 1 $ R $end
$var wire 1 ] S $end
$var reg 1 ^ Q $end
$upscope $end
$scope module _68_ $end
$var wire 1 # C $end
$var wire 1 _ D $end
$var wire 1 $ R $end
$var wire 1 ` S $end
$var reg 1 a Q $end
$upscope $end
$scope module _69_ $end
$var wire 1 # C $end
$var wire 1 b D $end
$var wire 1 $ R $end
$var wire 1 c S $end
$var reg 1 d Q $end
$upscope $end
$upscope $end
$upscope $end
$enddefinitions $end
$comment Show the parameter values. $end
$dumpall
$end
#0
$dumpvars
0d
0c
0b
0a
0`
0_
0^
0]
0\
0[
0Z
1Y
0X
0W
0V
0U
0T
0S
0R
0Q
1P
0O
0N
0M
1L
0K
0J
0I
1H
1G
1F
1E
1D
0C
0B
1A
0@
1?
0>
1=
1<
1;
0:
09
18
07
16
15
04
13
12
01
10
0/
1.
1-
0,
1+
0*
b1 )
b0 (
b0 '
b0 &
b1 %
1$
1#
0"
b0 !
$end
#100
0$
0#
b1 &
#200
1\
1S
0Y
0P
0<
b10 )
0L
1R
1Q
1K
b1 !
b1 '
b1 (
1[
1#
b10 %
b10 &
#300
0#
b11 &
#400
1\
0?
1S
1@
1C
1Y
1P
0<
0D
b11 )
1L
0G
0R
0Q
1O
1N
0K
1I
b10 !
b10 '
b10 (
0[
1^
1#
b11 %
b100 &
#500
0b
0\
0X
0_
0S
1+
b1 )
0V
1<
0,
12
13
1-
0@
0;
05
10
1?
1:
14
01
1B
19
0A
08
0H
0#
b101 &
1"
#600
0b
0X
1+
0_
0V
0,
1-
0=
13
10
0\
1>
01
1@
0;
0S
0?
1:
0Y
0P
0B
0<
1A
b0 )
0L
1G
1R
1Q
0O
0N
1K
0I
b1 !
b1 '
b1 (
1[
0^
1#
b100 %
b110 &
#700
0#
b111 &
#800
1b
1X
1_
0+
1V
1,
1\
03
00
0-
1S
1;
11
0>
0:
1Y
1P
1=
b1111 )
1L
0R
0Q
0K
b0 !
b0 '
b0 (
0[
1#
b101 %
b1000 &
#900
0#
b1001 &
#1000
1*
0;
0.
1:
1/
1>
0=
0Y
0P
17
06
0E
0L
0F
0G
1W
1U
1T
1R
1Q
1O
1N
1M
1K
1J
1I
b1111 !
b1111 '
b1111 (
1[
1^
1a
1d
0b
0X
0\
0_
0+
b0 )
0S
0V
1,
0<
13
0-
05
10
0?
1@
14
01
09
1C
0D
18
1H
1#
b110 %
b1010 &
0"
#1100
0#
b1011 &
#1200
0\
1+
0b
0S
1;
0,
1-
1<
1?
0X
0>
15
1.
04
0:
0/
0@
0C
0*
1Y
1P
07
16
1=
1D
b1 )
1E
1L
1F
1G
0W
0U
0T
0R
0Q
0O
0N
0M
0K
0J
0I
b0 !
b0 '
b0 (
0[
0^
0a
0d
1#
b111 %
b1100 &
#1300
0#
b1101 &
#1400
1\
1S
0Y
0P
0<
b10 )
0L
1R
1Q
1K
b1 !
b1 '
b1 (
1[
1#
b1000 %
b1110 &
#1500
0#
b1111 &
#1600
1\
0?
1S
1@
1C
1Y
1P
0<
0D
b11 )
1L
0G
0R
0Q
1O
1N
0K
1I
b10 !
b10 '
b10 (
0[
1^
1#
b1001 %
b10000 &
#1700
0#
b10001 &
#1800
1_
0\
1V
0S
0;
02
1>
1:
0Y
0P
0=
b100 )
0L
1R
1Q
1K
b11 !
b11 '
b11 (
1[
1#
b1010 %
b10010 &
#1900
0#
b10011 &
#2000
0b
0X
1_
0\
03
1+
1V
0S
1;
0,
12
1<
1?
0>
05
1.
14
0:
0@
0C
1Y
1P
17
06
1=
1D
b101 )
1L
0F
1G
1U
1T
0R
0Q
0O
0N
0K
1J
0I
b100 !
b100 '
b100 (
0[
0^
1a
1#
b1011 %
b10100 &
#2100
0#
b10101 &
#2200
1\
1S
0Y
0P
0<
b110 )
0L
1R
1Q
1K
b101 !
b101 '
b101 (
1[
1#
b1100 %
b10110 &
#2300
0#
b10111 &
#2400
1\
0?
1S
1@
1C
1Y
1P
0<
0D
b111 )
1L
0G
0R
0Q
1O
1N
0K
1I
b110 !
b110 '
b110 (
0[
1^
1#
b1101 %
b11000 &
#2500
0#
b11001 &
#2600
1b
0_
1X
0V
0+
0\
13
1,
0S
0;
0.
0-
1>
1:
1/
0Y
0P
0=
b1000 )
0L
1R
1Q
1K
b111 !
b111 '
b111 (
1[
1#
b1110 %
b11010 &
#2700
0#
b11011 &
#2800
0\
1b
0S
1;
0,
1-
1<
1?
1X
0>
15
1.
04
0:
0/
0@
0C
0*
1Y
1P
07
16
1=
1D
b1001 )
0E
1L
1F
1G
1W
0U
0T
0R
0Q
0O
0N
1M
0K
0J
0I
b1000 !
b1000 '
b1000 (
0[
0^
0a
1d
1#
b1111 %
b11100 &
#2900
0#
b11101 &
#3000
1\
1S
0Y
0P
0<
b1010 )
0L
1R
1Q
1K
b1001 !
b1001 '
b1001 (
1[
1#
b10000 %
b11110 &
#3100
0#
b11111 &
#3200
1\
0?
1S
1@
1C
1Y
1P
0<
0D
b1011 )
1L
0G
0R
0Q
1O
1N
0K
1I
b1010 !
b1010 '
b1010 (
0[
1^
1#
b10001 %
b100000 &
#3300
0#
b100001 &
#3400
1_
0\
1V
0S
0;
02
1>
1:
0Y
0P
0=
b1100 )
0L
1R
1Q
1K
b1011 !
b1011 '
b1011 (
1[
1#
b10010 %
b100010 &
#3500
0#
b100011 &
#3600
1_
0\
03
1V
0S
1;
0,
12
1<
1?
0>
05
1.
14
0:
0@
0C
1Y
1P
17
06
1=
1D
b1101 )
1L
0F
1G
1U
1T
0R
0Q
0O
0N
0K
1J
0I
b1100 !
b1100 '
b1100 (
0[
0^
1a
1#
b10011 %
b100100 &
#3700
0#
b100101 &
#3800
1\
1S
0Y
0P
0<
b1110 )
0L
1R
1Q
1K
b1101 !
b1101 '
b1101 (
1[
1#
b10100 %
b100110 &
#3900
0#
b100111 &
#4000
b101000 &
