sv/SystemVerilog/con03.08_stopwatch/stopwatch.v
module stopwatch (
	clk_i,
	reset_i,
	count_i,
	clear_i,
	time_o
);
	reg _sv2v_0;
	input wire clk_i;
	input wire reset_i;
	input wire count_i;
	input wire clear_i;
	output wire [7:0] time_o;
	reg state_p;
	reg state_n;
	reg [7:0] time_p;
	reg [7:0] time_n;
	always @(posedge clk_i or posedge reset_i)
		if (reset_i == 1) begin
			state_p <= 1'd0;
			time_p <= 0;
		end
		else begin
			state_p <= state_n;
			time_p <= time_n;
		end
	always @(*) begin
		if (_sv2v_0)
			;
		state_n = state_p;
		time_n = time_p;
		case (state_p)
			default: begin
				state_n = state_p;
				time_n = time_p;
			end
			1'd0: begin
				state_n = 1'd0;
				if (count_i)
					state_n = 1'd1;
			end
			1'd1: begin
				time_n = time_p + 1;
				state_n = 1'd1;
				if (count_i == 0)
					state_n = 1'd0;
				if (clear_i) begin
					time_n = 0;
					state_n = 1'd0;
				end
			end
		endcase
	end
	assign time_o = time_p;
	initial _sv2v_0 = 0;
endmodule

sv/SystemVerilog/con03.08_stopwatch/testbench.sv
`ifndef SYNTHESIS
module testbench();
  // wires for inputs to the module
  logic clk;
  logic reset;
  logic count;
  logic clearit;

  // wires for the outputs of the module
  logic [7:0] out;

  // Device-under-Test (DUT) instantiation
  stopwatch fsm(
    .clk_i(clk),
    .reset_i(reset),
    .count_i(count),
    .clear_i(clearit),
    .time_o(out)
  );

    // create dump file
  initial begin
    $dumpfile("stopwatch.vcd");
    $dumpvars(0, testbench);
  end

  // create clock
  integer cc = 0;
  integer i;
  initial begin
    clk = 0;

    for (i = 0; i < 40; i++) begin
      if (clk == 0)
        cc = cc + 1;

      clk = ~clk;
      #1;
    end

    $finish();
  end

  // handle reset
  initial reset = 1;
  always begin
    #1;
    reset = 0;
  end

  // testbench
  initial begin
    // executed whenever some value in the format string changes
    $monitor("time: %4d, clock cycle = %4d  reset_i = %d, out_o = %d", $time, cc, reset, out);

    clearit = 0;
    count = 0;
    #3;    
    count = 1;
    #10;
    clearit = 1;   
    #2;
    clearit = 0;
    count = 1;
    #4;
    clearit = 0;
  end
endmodule
`endif

sv/SystemVerilog/con03.08_stopwatch/stopwatch.vcd
$date
	Wed Oct 16 19:42:42 2024
$end
$version
	Icarus Verilog
$end
$timescale
	1s
$end
$scope module testbench $end
$var wire 8 ! out [7:0] $end
$var reg 1 " clearit $end
$var reg 1 # clk $end
$var reg 1 $ count $end
$var reg 1 % reset $end
$var integer 32 & cc [31:0] $end
$var integer 32 ' i [31:0] $end
$scope module fsm $end
$var wire 1 " clear_i $end
$var wire 1 # clk_i $end
$var wire 1 $ count_i $end
$var wire 1 % reset_i $end
$var wire 8 ( time_o [7:0] $end
$var reg 1 ) _sv2v_0 $end
$var reg 1 * state_n $end
$var reg 1 + state_p $end
$var reg 8 , time_n [7:0] $end
$var reg 8 - time_p [7:0] $end
$upscope $end
$upscope $end
$enddefinitions $end
$comment Show the parameter values. $end
$dumpall
$end
#0
$dumpvars
b0 -
b0 ,
0+
0*
0)
b0 (
b0 '
b1 &
1%
0$
1#
0"
b0 !
$end
#1
0%
0#
b1 '
#2
1#
b10 &
b10 '
#3
1*
0#
b11 '
1$
#4
b1 ,
1+
1#
b11 &
b100 '
#5
0#
b101 '
#6
b10 ,
b1 !
b1 (
b1 -
1#
b100 &
b110 '
#7
0#
b111 '
#8
b11 ,
b10 !
b10 (
b10 -
1#
b101 &
b1000 '
#9
0#
b1001 '
#10
b100 ,
b11 !
b11 (
b11 -
1#
b110 &
b1010 '
#11
0#
b1011 '
#12
b101 ,
b100 !
b100 (
b100 -
1#
b111 &
b1100 '
#13
0*
b0 ,
0#
b1101 '
1"
#14
1*
b0 !
b0 (
b0 -
0+
1#
b1000 &
b1110 '
#15
1*
0#
b1111 '
0"
#16
b1 ,
1+
1#
b1001 &
b10000 '
#17
0#
b10001 '
#18
b10 ,
b1 !
b1 (
b1 -
1#
b1010 &
b10010 '
#19
0#
b10011 '
#20
b11 ,
b10 !
b10 (
b10 -
1#
b1011 &
b10100 '
#21
0#
b10101 '
#22
b100 ,
b11 !
b11 (
b11 -
1#
b1100 &
b10110 '
#23
0#
b10111 '
#24
b101 ,
b100 !
b100 (
b100 -
1#
b1101 &
b11000 '
#25
0#
b11001 '
#26
b110 ,
b101 !
b101 (
b101 -
1#
b1110 &
b11010 '
#27
0#
b11011 '
#28
b111 ,
b110 !
b110 (
b110 -
1#
b1111 &
b11100 '
#29
0#
b11101 '
#30
b1000 ,
b111 !
b111 (
b111 -
1#
b10000 &
b11110 '
#31
0#
b11111 '
#32
b1001 ,
b1000 !
b1000 (
b1000 -
1#
b10001 &
b100000 '
#33
0#
b100001 '
#34
b1010 ,
b1001 !
b1001 (
b1001 -
1#
b10010 &
b100010 '
#35
0#
b100011 '
#36
b1011 ,
b1010 !
b1010 (
b1010 -
1#
b10011 &
b100100 '
#37
0#
b100101 '
#38
b1100 ,
b1011 !
b1011 (
b1011 -
1#
b10100 &
b100110 '
#39
0#
b100111 '
#40
b101000 '
